LICENSE
MANIFEST.in
README.rst
pyproject.toml
setup.cfg
setup.py
cffi/build.py
cffi/cdefs.h
cffi/source.c
libyang/__init__.py
libyang/context.py
libyang/data.py
libyang/diff.py
libyang/extension.py
libyang/keyed_list.py
libyang/log.py
libyang/py.typed
libyang/schema.py
libyang/util.py
libyang/xpath.py
libyang.egg-info/PKG-INFO
libyang.egg-info/SOURCES.txt
libyang.egg-info/dependency_links.txt
libyang.egg-info/not-zip-safe
libyang.egg-info/requires.txt
libyang.egg-info/top_level.txt
tests/test_context.py
tests/test_data.py
tests/test_diff.py
tests/test_extension.py
tests/test_keyedlist.py
tests/test_log.py
tests/test_schema.py
tests/test_xpath.py