Metadata-Version: 2.4
Name: libyang
Version: 3.3.0
Summary: CFFI bindings to libyang
Home-page: https://github.com/CESNET/libyang-python
Author: Robin Jarry
Author-email: robin@jarry.cc
License: MIT
Keywords: libyang,cffi
Classifier: Development Status :: 4 - Beta
Classifier: Environment :: Console
Classifier: Intended Audience :: Developers
Classifier: License :: OSI Approved :: MIT License
Classifier: Operating System :: Unix
Classifier: Programming Language :: Python :: 3
Classifier: Topic :: Software Development :: Libraries
Requires-Python: >=3.6
License-File: LICENSE
Requires-Dist: cffi; platform_python_implementation != "PyPy"
Dynamic: author
Dynamic: author-email
Dynamic: classifier
Dynamic: description
Dynamic: home-page
Dynamic: keywords
Dynamic: license
Dynamic: license-file
Dynamic: requires-dist
Dynamic: requires-python
Dynamic: summary
